falmark4.py
Falmark/__init__.py
Falmark-1.1.0.dist-info/METADATA
Falmark-1.1.0.dist-info/WHEEL
Falmark-1.1.0.dist-info/entry_points.txt
Falmark-1.1.0.dist-info/top_level.txt
Falmark-1.1.0.dist-info/RECORD
